{
 "100101": "Special Week (Special Dreamer)",
 "100102": "Special Week (Hopp'n♪Happy Heart)",
 "100103": "Special Week (Ruler of Japan)",
 "100201": "Silence Suzuka (Innocent Silence)",
 "100301": "Tokai Teio (Peak Joy)",
 "100302": "Tokai Teio (Beyond the Horizon)",
 "100401": "Maruzensky (Formula R)",
 "100402": "Maruzensky (Hot☆Summer Night)",
 "100501": "Fuji Kiseki (Shooting Star Revue)",
 "100502": "Fuji Kiseki (Succès Étoilé)",
 "100601": "Oguri Cap (Starlight Beat)",
 "100602": "Oguri Cap (Ashen Miracle)",
 "100701": "Gold Ship (Red Strife)",
 "100801": "Vodka (Wild Top Gear)",
 "100901": "Daiwa Scarlet (Peak Blue)",
 "101001": "Taiki Shuttle (Wild Frontier)",
 "101002": "Taiki Shuttle (Bubblegum☆Memories)",
 "101101": "Grass Wonder (Stone-Piercing Blue)",
 "101102": "Grass Wonder (Saintly Jade Cleric)",
 "101201": "Hishi Amazon (Azure Amazon)",
 "101301": "Mejiro McQueen (Frontline Elegance)",
 "101302": "Mejiro McQueen (End of the Skies)",
 "101401": "El Condor Pasa (El☆Número 1)",
 "101402": "El Condor Pasa (Kukulkan Warrior)",
 "101501": "T.M. Opera O (O Sole Suo!)",
 "101502": "T.M. Opera O (New Year, Same Radiance!)",
 "101601": "Narita Brian (Maverick)",
 "101701": "Symboli Rudolf (Emperor's Path)",
 "101702": "Symboli Rudolf (Archer by Moonlight)",
 "101801": "Air Groove (Empress Road)",
 "101802": "Air Groove (Quercus Civilis)",
 "101901": "Agnes Digital (Full-Color Fangirling)",
 "102001": "Seiun Sky (Reeling in the Big One)",
 "102002": "Seiun Sky (Soirée des Chatons)",
 "102101": "Tamamo Cross (Fast as Lightning)",
 "102201": "Fine Motion (Noble Seamair)",
 "102202": "Fine Motion (Titania)",
 "102301": "Biwa Hayahide (pf. Winning Equation...)",
 "102302": "Biwa Hayahide (Rouge Caroler)",
 "102401": "Mayano Top Gun (Scramble☆Zone)",
 "102402": "Mayano Top Gun (Sunlight Bouquet)",
 "102501": "Manhattan Cafe (Creeping Shadow)",
 "102601": "Mihono Bourbon (MB-19890425)",
 "102602": "Mihono Bourbon (CODE: ICING)",
 "102701": "Mejiro Ryan (Down the Line)",
 "102801": "Hishi Akebono (Buono ☆ Alla Moda)",
 "103001": "Rice Shower (Rosy Dreams)",
 "103002": "Rice Shower (Vampire Makeover!)",
 "103101": "Ines Fujin (Always Electrifying)",
 "103201": "Agnes Tachyon (Tach-nology)",
 "103301": "Admire Vega (Starry Nocturne)",
 "103401": "Inari One (Edomurasaki)",
 "103501": "Winning Ticket (Get to Winning!)",
 "103601": "Air Shakur (unsigned)",
 "103701": "Eishin Flash (Meisterschaft)",
 "103702": "Eishin Flash (Precise Chocolatier)",
 "103801": "Curren Chan (Fille Éclair)",
 "103802": "Curren Chan (Ma Chérie of the New Moon)",
 "103901": "Kawakami Princess (Princess of Pink)",
 "104001": "Gold City (Authentic / 1928)",
 "104002": "Gold City (Autumn Cosmos)",
 "104101": "Sakura Bakushin O (Blossom in Learning)",
 "104401": "Sweep Tosho (Platanus Witch)",
 "104501": "Super Creek (Murmuring Stream)",
 "104502": "Super Creek (Chiffon-Wrapped Mummy)",
 "104601": "Smart Falcon (LOVE☆4EVER)",
 "104801": "Tosen Jordan (Jokester ☆ Vibes)",
 "105001": "Narita Taishin (Nevertheless)",
 "105101": "Nishino Flower (Layered Petals)",
 "105201": "Haru Urara (Bestest Prize ♪)",
 "105202": "Haru Urara (New Year ♪ New Urara!)",
 "105601": "Matikanefukukitaru (Rising☆Fortune)",
 "105602": "Matikanefukukitaru (Lucky Tidings)",
 "105801": "Meisho Doto (Turbulent Blue)",
 "105901": "Mejiro Dober (Off the Line)",
 "105902": "Mejiro Dober (Sapphire Sojourn)",
 "106001": "Nice Nature (Poinsettia Ribbon)",
 "106002": "Nice Nature (Run & Win)",
 "106101": "King Halo (King of Emeralds)",
 "106102": "King Halo (Cheerleader in Noble White)",
 "106201": "Matikanetannhauser (Clippety-Tippety-Clop)",
 "106401": "Mejiro Palmer (Line Breakthrough)",
 "106701": "Satono Diamond (Natural Brilliance)",
 "106801": "Kitasan Black (Gilded Shrine to Glory)",
 "106901": "Sakura Chiyono O (Strength in Full Bloom)",
 "107101": "Mejiro Ardan (Crystalline)",
 "107201": "Yaeno Muteki (Blazed Head, Covered Fists)",
 "107401": "Mejiro Bright (Brunissage Line)",
 "9100101": "Special Week (Special Dreamer)",
 "9101101": "Grass Wonder (Stone-Piercing Blue)"
}